{"title": "Mr. Penguin", "id": "tg-858174108288942090", "net.maunium.telegram.pack": {"short_name": "MrPenguin", "hash": "-1478105995"}, "stickers": [{"body": "😂", "url": "mxc://matrix.org/OSxiXDMUsazWEbWihFlVipuL", "info": {"w": 256, "h": 256, "size": 213732, "mimetype": "image/png", "thumbnail_url": "mxc://matrix.org/OSxiXDMUsazWEbWihFlVipuL", "thumbnail_info": {"w": 256, "h": 256, "size": 213732, "mimetype": "image/png"}}, "msgtype": "m.sticker", "id": "tg-858174108288942872", "net.maunium.telegram.sticker": {"pack": {"id": "858174108288942090", "short_name": "MrPenguin"}, "id": "858174108288942872", "emoticons": ["😂", "😆"]}}, {"body": "😘", "url": "mxc://matrix.org/yHCKmeDxVGzTVujiQGdXknAT", "info": {"w": 256, "h": 256, "size": 343609, "mimetype": "image/png", "thumbnail_url": "mxc://matrix.org/yHCKmeDxVGzTVujiQGdXknAT", "thumbnail_info": {"w": 256, "h": 256, "size": 343609, "mimetype": "image/png"}}, "msgtype": "m.sticker", "id": "tg-858174108288942874", "net.maunium.telegram.sticker": {"pack": {"id": "858174108288942090", "short_name": "MrPenguin"}, "id": "858174108288942874", "emoticons": ["😘", "❤"]}}, {"body": "👍", "url": "mxc://matrix.org/vfvHowgTQlwgXdXeaHnpOfGq", "info": {"w": 256, "h": 256, "size": 206169, "mimetype": "image/png", "thumbnail_url": "mxc://matrix.org/vfvHowgTQlwgXdXeaHnpOfGq", "thumbnail_info": {"w": 256, "h": 256, "size": 206169, "mimetype": "image/png"}}, "msgtype": "m.sticker", "id": "tg-858174108288942870", "net.maunium.telegram.sticker": {"pack": {"id": "858174108288942090", "short_name": "MrPenguin"}, "id": "858174108288942870", "emoticons": ["👍"]}}, {"body": "😨", "url": "mxc://matrix.org/hmtkbXYKAzZvHGHEmOuxeFtC", "info": {"w": 256, "h": 256, "size": 302301, "mimetype": "image/png", "thumbnail_url": "mxc://matrix.org/hmtkbXYKAzZvHGHEmOuxeFtC", "thumbnail_info": {"w": 256, "h": 256, "size": 302301, "mimetype": "image/png"}}, "msgtype": "m.sticker", "id": "tg-858174108288942901", "net.maunium.telegram.sticker": {"pack": {"id": "858174108288942090", "short_name": "MrPenguin"}, "id": "858174108288942901", "emoticons": ["😨"]}}, {"body": "👋", "url": "mxc://matrix.org/AcuuCTAoLFkNLCPCMvDuKJAo", "info": {"w": 256, "h": 256, "size": 205571, "mimetype": "image/png", "thumbnail_url": "mxc://matrix.org/AcuuCTAoLFkNLCPCMvDuKJAo", "thumbnail_info": {"w": 256, "h": 256, "size": 205571, "mimetype": "image/png"}}, "msgtype": "m.sticker", "id": "tg-858174108288943176", "net.maunium.telegram.sticker": {"pack": {"id": "858174108288942090", "short_name": "MrPenguin"}, "id": "858174108288943176", "emoticons": ["👋"]}}, {"body": "😵", "url": "mxc://matrix.org/efOPPlhFfOPnLFqdZZORHHeI", "info": {"w": 256, "h": 256, "size": 265205, "mimetype": "image/png", "thumbnail_url": "mxc://matrix.org/efOPPlhFfOPnLFqdZZORHHeI", "thumbnail_info": {"w": 256, "h": 256, "size": 265205, "mimetype": "image/png"}}, "msgtype": "m.sticker", "id": "tg-858174108288942903", "net.maunium.telegram.sticker": {"pack": {"id": "858174108288942090", "short_name": "MrPenguin"}, "id": "858174108288942903", "emoticons": ["😵"]}}, {"body": "🌈", "url": "mxc://matrix.org/TAaZfVkwDzphInTaUDQdZqVD", "info": {"w": 256, "h": 256, "size": 301247, "mimetype": "image/png", "thumbnail_url": "mxc://matrix.org/TAaZfVkwDzphInTaUDQdZqVD", "thumbnail_info": {"w": 256, "h": 256, "size": 301247, "mimetype": "image/png"}}, "msgtype": "m.sticker", "id": "tg-858174108288942920", "net.maunium.telegram.sticker": {"pack": {"id": "858174108288942090", "short_name": "MrPenguin"}, "id": "858174108288942920", "emoticons": ["🌈", "😄"]}}, {"body": "❌", "url": "mxc://matrix.org/DYTZQsjPFqMYxexRkUEqpiNJ", "info": {"w": 256, "h": 256, "size": 175368, "mimetype": "image/png", "thumbnail_url": "mxc://matrix.org/DYTZQsjPFqMYxexRkUEqpiNJ", "thumbnail_info": {"w": 256, "h": 256, "size": 175368, "mimetype": "image/png"}}, "msgtype": "m.sticker", "id": "tg-858174108288942876", "net.maunium.telegram.sticker": {"pack": {"id": "858174108288942090", "short_name": "MrPenguin"}, "id": "858174108288942876", "emoticons": ["❌"]}}, {"body": "🤗", "url": "mxc://matrix.org/pkepipMyBgBgGykJTlXwNdRa", "info": {"w": 256, "h": 256, "size": 288468, "mimetype": "image/png", "thumbnail_url": "mxc://matrix.org/pkepipMyBgBgGykJTlXwNdRa", "thumbnail_info": {"w": 256, "h": 256, "size": 288468, "mimetype": "image/png"}}, "msgtype": "m.sticker", "id": "tg-858174108288942909", "net.maunium.telegram.sticker": {"pack": {"id": "858174108288942090", "short_name": "MrPenguin"}, "id": "858174108288942909", "emoticons": ["🤗"]}}, {"body": "🌹", "url": "mxc://matrix.org/kkKJefzQMRmROcvTlnxZIfLM", "info": {"w": 256, "h": 256, "size": 267157, "mimetype": "image/png", "thumbnail_url": "mxc://matrix.org/kkKJefzQMRmROcvTlnxZIfLM", "thumbnail_info": {"w": 256, "h": 256, "size": 267157, "mimetype": "image/png"}}, "msgtype": "m.sticker", "id": "tg-858174108288942899", "net.maunium.telegram.sticker": {"pack": {"id": "858174108288942090", "short_name": "MrPenguin"}, "id": "858174108288942899", "emoticons": ["🌹"]}}, {"body": "🚬", "url": "mxc://matrix.org/EDuwGUraSClaWuncYtIobQTg", "info": {"w": 256, "h": 256, "size": 258593, "mimetype": "image/png", "thumbnail_url": "mxc://matrix.org/EDuwGUraSClaWuncYtIobQTg", "thumbnail_info": {"w": 256, "h": 256, "size": 258593, "mimetype": "image/png"}}, "msgtype": "m.sticker", "id": "tg-858174108288942881", "net.maunium.telegram.sticker": {"pack": {"id": "858174108288942090", "short_name": "MrPenguin"}, "id": "858174108288942881", "emoticons": ["🚬"]}}, {"body": "💩", "url": "mxc://matrix.org/dfvHmkXpVMjwXbyrUIDCtXEI", "info": {"w": 256, "h": 256, "size": 260712, "mimetype": "image/png", "thumbnail_url": "mxc://matrix.org/dfvHmkXpVMjwXbyrUIDCtXEI", "thumbnail_info": {"w": 256, "h": 256, "size": 260712, "mimetype": "image/png"}}, "msgtype": "m.sticker", "id": "tg-858174108288942883", "net.maunium.telegram.sticker": {"pack": {"id": "858174108288942090", "short_name": "MrPenguin"}, "id": "858174108288942883", "emoticons": ["💩"]}}, {"body": "👏", "url": "mxc://matrix.org/JqBSHUHqgnkkxLBjXXCvNRjZ", "info": {"w": 256, "h": 256, "size": 220502, "mimetype": "image/png", "thumbnail_url": "mxc://matrix.org/JqBSHUHqgnkkxLBjXXCvNRjZ", "thumbnail_info": {"w": 256, "h": 256, "size": 220502, "mimetype": "image/png"}}, "msgtype": "m.sticker", "id": "tg-858174108288942887", "net.maunium.telegram.sticker": {"pack": {"id": "858174108288942090", "short_name": "MrPenguin"}, "id": "858174108288942887", "emoticons": ["👏", "😐"]}}, {"body": "😭", "url": "mxc://matrix.org/qGzkMBDKhyefaQMEQiSigTgc", "info": {"w": 256, "h": 256, "size": 334172, "mimetype": "image/png", "thumbnail_url": "mxc://matrix.org/qGzkMBDKhyefaQMEQiSigTgc", "thumbnail_info": {"w": 256, "h": 256, "size": 334172, "mimetype": "image/png"}}, "msgtype": "m.sticker", "id": "tg-858174108288942889", "net.maunium.telegram.sticker": {"pack": {"id": "858174108288942090", "short_name": "MrPenguin"}, "id": "858174108288942889", "emoticons": ["😭"]}}, {"body": "😩", "url": "mxc://matrix.org/IugaqKWKgLpJnrJThWBIaeSQ", "info": {"w": 256, "h": 256, "size": 234674, "mimetype": "image/png", "thumbnail_url": "mxc://matrix.org/IugaqKWKgLpJnrJThWBIaeSQ", "thumbnail_info": {"w": 256, "h": 256, "size": 234674, "mimetype": "image/png"}}, "msgtype": "m.sticker", "id": "tg-858174108288942891", "net.maunium.telegram.sticker": {"pack": {"id": "858174108288942090", "short_name": "MrPenguin"}, "id": "858174108288942891", "emoticons": ["😩", "😖"]}}, {"body": "🙄", "url": "mxc://matrix.org/NRkGXYNBpyctnosGmUIzCJUb", "info": {"w": 256, "h": 256, "size": 209306, "mimetype": "image/png", "thumbnail_url": "mxc://matrix.org/NRkGXYNBpyctnosGmUIzCJUb", "thumbnail_info": {"w": 256, "h": 256, "size": 209306, "mimetype": "image/png"}}, "msgtype": "m.sticker", "id": "tg-858174108288942893", "net.maunium.telegram.sticker": {"pack": {"id": "858174108288942090", "short_name": "MrPenguin"}, "id": "858174108288942893", "emoticons": ["🙄"]}}, {"body": "😡", "url": "mxc://matrix.org/QMBwFDLeZciLqhZlXrIlsjmF", "info": {"w": 256, "h": 256, "size": 306745, "mimetype": "image/png", "thumbnail_url": "mxc://matrix.org/QMBwFDLeZciLqhZlXrIlsjmF", "thumbnail_info": {"w": 256, "h": 256, "size": 306745, "mimetype": "image/png"}}, "msgtype": "m.sticker", "id": "tg-858174108288942895", "net.maunium.telegram.sticker": {"pack": {"id": "858174108288942090", "short_name": "MrPenguin"}, "id": "858174108288942895", "emoticons": ["😡", "🔥"]}}, {"body": "🤔", "url": "mxc://matrix.org/AmbhScFLwFstHWZwwcLtfslg", "info": {"w": 256, "h": 256, "size": 195294, "mimetype": "image/png", "thumbnail_url": "mxc://matrix.org/AmbhScFLwFstHWZwwcLtfslg", "thumbnail_info": {"w": 256, "h": 256, "size": 195294, "mimetype": "image/png"}}, "msgtype": "m.sticker", "id": "tg-858174108288942905", "net.maunium.telegram.sticker": {"pack": {"id": "858174108288942090", "short_name": "MrPenguin"}, "id": "858174108288942905", "emoticons": ["🤔"]}}, {"body": "🖕", "url": "mxc://matrix.org/fdTXNCWNTruoZKldHoivcFIC", "info": {"w": 256, "h": 256, "size": 314525, "mimetype": "image/png", "thumbnail_url": "mxc://matrix.org/fdTXNCWNTruoZKldHoivcFIC", "thumbnail_info": {"w": 256, "h": 256, "size": 314525, "mimetype": "image/png"}}, "msgtype": "m.sticker", "id": "tg-858174108288942907", "net.maunium.telegram.sticker": {"pack": {"id": "858174108288942090", "short_name": "MrPenguin"}, "id": "858174108288942907", "emoticons": ["🖕"]}}, {"body": "😊", "url": "mxc://matrix.org/fhxhTjwNlVarTmNxrGkLDaAA", "info": {"w": 256, "h": 256, "size": 189472, "mimetype": "image/png", "thumbnail_url": "mxc://matrix.org/fhxhTjwNlVarTmNxrGkLDaAA", "thumbnail_info": {"w": 256, "h": 256, "size": 189472, "mimetype": "image/png"}}, "msgtype": "m.sticker", "id": "tg-858174108288942911", "net.maunium.telegram.sticker": {"pack": {"id": "858174108288942090", "short_name": "MrPenguin"}, "id": "858174108288942911", "emoticons": ["😊"]}}, {"body": "😏", "url": "mxc://matrix.org/epGyHnimSxuvLVqihFZYxBSf", "info": {"w": 256, "h": 256, "size": 236497, "mimetype": "image/png", "thumbnail_url": "mxc://matrix.org/epGyHnimSxuvLVqihFZYxBSf", "thumbnail_info": {"w": 256, "h": 256, "size": 236497, "mimetype": "image/png"}}, "msgtype": "m.sticker", "id": "tg-858174108288942913", "net.maunium.telegram.sticker": {"pack": {"id": "858174108288942090", "short_name": "MrPenguin"}, "id": "858174108288942913", "emoticons": ["😏"]}}, {"body": "🙅", "url": "mxc://matrix.org/iGmYvhwTRhTqVhAFdJQcNHrX", "info": {"w": 256, "h": 256, "size": 221716, "mimetype": "image/png", "thumbnail_url": "mxc://matrix.org/iGmYvhwTRhTqVhAFdJQcNHrX", "thumbnail_info": {"w": 256, "h": 256, "size": 221716, "mimetype": "image/png"}}, "msgtype": "m.sticker", "id": "tg-858174108288942915", "net.maunium.telegram.sticker": {"pack": {"id": "858174108288942090", "short_name": "MrPenguin"}, "id": "858174108288942915", "emoticons": ["🙅"]}}, {"body": "💥", "url": "mxc://matrix.org/VBPnzCgFBSkKLyXXfDEGHGiE", "info": {"w": 256, "h": 256, "size": 257296, "mimetype": "image/png", "thumbnail_url": "mxc://matrix.org/VBPnzCgFBSkKLyXXfDEGHGiE", "thumbnail_info": {"w": 256, "h": 256, "size": 257296, "mimetype": "image/png"}}, "msgtype": "m.sticker", "id": "tg-858174108288942922", "net.maunium.telegram.sticker": {"pack": {"id": "858174108288942090", "short_name": "MrPenguin"}, "id": "858174108288942922", "emoticons": ["💥", "☠"]}}, {"body": "🏋", "url": "mxc://matrix.org/cdMVIAIkRYoRRtTKtfYdKdfP", "info": {"w": 256, "h": 256, "size": 247118, "mimetype": "image/png", "thumbnail_url": "mxc://matrix.org/cdMVIAIkRYoRRtTKtfYdKdfP", "thumbnail_info": {"w": 256, "h": 256, "size": 247118, "mimetype": "image/png"}}, "msgtype": "m.sticker", "id": "tg-858174108288942924", "net.maunium.telegram.sticker": {"pack": {"id": "858174108288942090", "short_name": "MrPenguin"}, "id": "858174108288942924", "emoticons": ["🏋", "🍕"]}}, {"body": "🚣", "url": "mxc://matrix.org/ibOtXBgGpwGXwGZoikjTciWb", "info": {"w": 256, "h": 256, "size": 243964, "mimetype": "image/png", "thumbnail_url": "mxc://matrix.org/ibOtXBgGpwGXwGZoikjTciWb", "thumbnail_info": {"w": 256, "h": 256, "size": 243964, "mimetype": "image/png"}}, "msgtype": "m.sticker", "id": "tg-858174108288942928", "net.maunium.telegram.sticker": {"pack": {"id": "858174108288942090", "short_name": "MrPenguin"}, "id": "858174108288942928", "emoticons": ["🚣", "❓"]}}, {"body": "🔥", "url": "mxc://matrix.org/ziHDzwpVORgiNEUAsCdWHMZC", "info": {"w": 256, "h": 256, "size": 247836, "mimetype": "image/png", "thumbnail_url": "mxc://matrix.org/ziHDzwpVORgiNEUAsCdWHMZC", "thumbnail_info": {"w": 256, "h": 256, "size": 247836, "mimetype": "image/png"}}, "msgtype": "m.sticker", "id": "tg-858174108288942926", "net.maunium.telegram.sticker": {"pack": {"id": "858174108288942090", "short_name": "MrPenguin"}, "id": "858174108288942926", "emoticons": ["🔥"]}}, {"body": "😰", "url": "mxc://matrix.org/GvaIsaEUKGBBChWPZLJmFmys", "info": {"w": 256, "h": 256, "size": 233184, "mimetype": "image/png", "thumbnail_url": "mxc://matrix.org/GvaIsaEUKGBBChWPZLJmFmys", "thumbnail_info": {"w": 256, "h": 256, "size": 233184, "mimetype": "image/png"}}, "msgtype": "m.sticker", "id": "tg-858174108288942934", "net.maunium.telegram.sticker": {"pack": {"id": "858174108288942090", "short_name": "MrPenguin"}, "id": "858174108288942934", "emoticons": ["😰", "😱"]}}, {"body": "🍾", "url": "mxc://matrix.org/GeHxpdIwthjFeYCJedSXepdp", "info": {"w": 256, "h": 256, "size": 245338, "mimetype": "image/png", "thumbnail_url": "mxc://matrix.org/GeHxpdIwthjFeYCJedSXepdp", "thumbnail_info": {"w": 256, "h": 256, "size": 245338, "mimetype": "image/png"}}, "msgtype": "m.sticker", "id": "tg-858174108288942937", "net.maunium.telegram.sticker": {"pack": {"id": "858174108288942090", "short_name": "MrPenguin"}, "id": "858174108288942937", "emoticons": ["🍾", "🛁"]}}, {"body": "😸", "url": "mxc://matrix.org/bNHrKMQLLDBaOAuEUleBRNCy", "info": {"w": 256, "h": 256, "size": 247896, "mimetype": "image/png", "thumbnail_url": "mxc://matrix.org/bNHrKMQLLDBaOAuEUleBRNCy", "thumbnail_info": {"w": 256, "h": 256, "size": 247896, "mimetype": "image/png"}}, "msgtype": "m.sticker", "id": "tg-858174108288942939", "net.maunium.telegram.sticker": {"pack": {"id": "858174108288942090", "short_name": "MrPenguin"}, "id": "858174108288942939", "emoticons": ["😊", "😸"]}}, {"body": "😢", "url": "mxc://matrix.org/yFqyHMemsLlkpzpvKTbMBUFU", "info": {"w": 256, "h": 256, "size": 148132, "mimetype": "image/png", "thumbnail_url": "mxc://matrix.org/yFqyHMemsLlkpzpvKTbMBUFU", "thumbnail_info": {"w": 256, "h": 256, "size": 148132, "mimetype": "image/png"}}, "msgtype": "m.sticker", "id": "tg-858174108288942941", "net.maunium.telegram.sticker": {"pack": {"id": "858174108288942090", "short_name": "MrPenguin"}, "id": "858174108288942941", "emoticons": ["😢", "😥"]}}, {"body": "🌅", "url": "mxc://matrix.org/nosHAHlmwMmozibqXxvpXBon", "info": {"w": 256, "h": 256, "size": 198259, "mimetype": "image/png", "thumbnail_url": "mxc://matrix.org/nosHAHlmwMmozibqXxvpXBon", "thumbnail_info": {"w": 256, "h": 256, "size": 198259, "mimetype": "image/png"}}, "msgtype": "m.sticker", "id": "tg-858174108288942943", "net.maunium.telegram.sticker": {"pack": {"id": "858174108288942090", "short_name": "MrPenguin"}, "id": "858174108288942943", "emoticons": ["🚣", "🌅"]}}]}